<odoo>
  <data>
    <!-- explicit list view definition -->


    <!-- actions opening views on models -->


    <!-- server action to the one above -->
<!--
    <record model="ir.actions.server" id="f1.action_server">
      <field name="name">F1 server</field>
      <field name="model_id" ref="model_f1_f1"/>
      <field name="state">code</field>
      <field name="code">
        action = {
          "type": "ir.actions.act_window",
          "view_mode": "tree,form",
          "res_model": model._name,
        }
      </field>
    </record>
-->

    <!-- Top menu item -->

    <menuitem name="F1" id="f1.menu_root"/>

    <!-- menu categories -->

    <menuitem name="Menu 1" id="f1.menu_1" parent="f1.menu_root"/>

    <!-- actions -->


  </data>
</odoo>